{
  "category": "Mathematics",
  "modules": [
    {

      "name": "Module 1",
      "question": "What is 2+2?",
      "description": "This is module 1",
      "answeredCorrectlyCount": 0,
      "answeredIncorrectlyCount": 0,
      "answers": [
        {
          "0": 1,
          "1": 2,
          "2": 3,
          "3": 4
        }
      ],
      "correctAnswer": 4
    },
    {
      "name": "Module 2",
      "question": "What is 3+2?",
      "description": "This is module 2",
      "answeredCorrectlyCount": 0,
      "answeredIncorrectlyCount": 0,
      "answers": [
        {
          "0": 5,
          "1": 6,
          "2": 7,
          "3": 8
        }
      ],
      "correctAnswer": 5
    },
    {
      "name": "Module 3",
      "question": "What is 5+5?",
      "description": "This is module 3",
      "answeredCorrectlyCount": 0,
      "answeredIncorrectlyCount": 0,
      "answers": [
        {
          "0": 10,
          "1": 11,
          "2": 12,
          "3": 13
        }
      ],
      "correctAnswers": 10
    },
    {
      "name": "Module 4",
      "question": "What is 8+7?",
      "description": "This is module 4",
      "answeredCorrectlyCount": 0,
      "answeredIncorrectlyCount": 0,
      "answers": [
        {
          "0": 15,
          "1": 16,
          "2": 17,
          "3": 18
        }
      ],
      "correctAnswer": 15
    },
    {
      "name": "Module 5",
      "question": "What is 10+10?",
      "description": "This is module 5",
      "answeredCorrectlyCount": 0,
      "answeredIncorrectlyCount": 0,
      "answers": [
        {
          "0": 20,
          "1": 21,
          "2": 22,
          "3": 23
        }
      ],
      "correctAnswer": 20
    },
    {
      "name": "Module 6",
      "question": "What is 2*2?",
      "description": "This is module 6",
      "answeredCorrectlyCount": 0,
      "answeredIncorrectlyCount": 0,
      "answers": [
        {
          "0": 2,
          "1": 4,
          "2": 6,
          "3": 8
        }
      ],
      "correctAnswer": 4
    }
  ]
}
